Metadata-Version: 2.1
Name: th2-grpc-act-gui-demo
Version: 2.1.5
Summary: th2_grpc_act_gui_demo
Home-page: https://gitlab.exactpro.com/vivarium/th2/th2-core-open-source/th2-grpc-act-gui-demo
Author: TH2-devs
Author-email: th2-devs@exactprosystems.com
License: Apache License 2.0
Platform: UNKNOWN
Requires-Python: >=3.7
